sketchKH/__init__.py
sketchKH/kh.py
sketchKH-0.1.2.dist-info/LICENSE
sketchKH-0.1.2.dist-info/METADATA
sketchKH-0.1.2.dist-info/WHEEL
sketchKH-0.1.2.dist-info/top_level.txt
sketchKH-0.1.2.dist-info/RECORD
