Metadata-Version: 2.1
Name: sketchKH
Version: 0.1.2
Summary: Distribution-based sketching of single-cell samples
Home-page: https://github.com/CompCy-lab/SketchKH
Author: CompCy Lab
Author-email: compcylab@gmail.com
License: MIT
Keywords: cytometry,single-cell bioinformatics,clinical prediction,compression,computational biology
Classifier: Development Status :: 3 - Alpha
Classifier: Intended Audience :: Science/Research
Classifier: Topic :: Scientific/Engineering :: Bio-Informatics
Classifier: License :: OSI Approved :: MIT License
Classifier: Programming Language :: Python :: 3.6
Classifier: Programming Language :: Python :: 3.7
Classifier: Programming Language :: Python :: 3.8
Classifier: Programming Language :: Python :: 3.9
Classifier: Operating System :: OS Independent
Requires-Python: >=3.6, <3.10
License-File: LICENSE
Requires-Dist: anndata (>=0.7.6)
Requires-Dist: numpy (>=1.22.4)
Requires-Dist: scipy (>=1.7.1)
Requires-Dist: numba
Requires-Dist: tqdm
Requires-Dist: joblib
Requires-Dist: tqdm-joblib
